<?xml version="1.0" encoding="UTF-8"?>
<XAG>

	<historique>
		<date>2009/01/01</date>
		<taux1>8.7879855500</taux1>
		<taux2>0.1237807817</taux2>
	</historique>

	<historique>
		<date>2009/01/02</date>
		<taux1>8.3123434984</taux1>
		<taux2>0.1203030169</taux2>
	</historique>

	<historique>
		<date>2009/01/02</date>
		<taux1>8.3123434984</taux1>
		<taux2>0.1203030169</taux2>
	</historique>

	<historique>
		<date>2009/01/03</date>
		<taux1>8.3589071449</taux1>
		<taux2>0.1196328638</taux2>
	</historique>

	<historique>
		<date>2009/01/04</date>
		<taux1>8.3258999199</taux1>
		<taux2>0.1201071367</taux2>
	</historique>

	<historique>
		<date>2009/01/05</date>
		<taux1>8.2659877583</taux1>
		<taux2>0.1209776773</taux2>
	</historique>

	<historique>
		<date>2009/01/06</date>
		<taux1>8.5197357366</taux1>
		<taux2>0.1173745326</taux2>
	</historique>

	<historique>
		<date>2009/01/07</date>
		<taux1>8.6532638500</taux1>
		<taux2>0.1239875428</taux2>
	</historique>

	<historique>
		<date>2009/01/08</date>
		<taux1>8.1018186292</taux1>
		<taux2>0.1234290776</taux2>
	</historique>

	<historique>
		<date>2009/01/09</date>
		<taux1>8.4314936928</taux1>
		<taux2>0.1186029470</taux2>
	</historique>

	<historique>
		<date>2009/01/10</date>
		<taux1>8.3839146704</taux1>
		<taux2>0.1192760231</taux2>
	</historique>

	<historique>
		<date>2009/01/11</date>
		<taux1>8.3708642044</taux1>
		<taux2>0.1194619785</taux2>
	</historique>

	<historique>
		<date>2009/01/12</date>
		<taux1>7.9309424182</taux1>
		<taux2>0.1260884202</taux2>
	</historique>

	<historique>
		<date>2009/01/13</date>
		<taux1>8.1547571667</taux1>
		<taux2>0.1226278085</taux2>
	</historique>

	<historique>
		<date>2009/01/14</date>
		<taux1>8.3916324020</taux1>
		<taux2>0.1243910554</taux2>
	</historique>

	<historique>
		<date>2009/01/15</date>
		<taux1>8.6772052360</taux1>
		<taux2>0.1239507488</taux2>
	</historique>

	<historique>
		<date>2009/01/16</date>
		<taux1>8.4726758820</taux1>
		<taux2>0.1180264670</taux2>
	</historique>

	<historique>
		<date>2009/01/17</date>
		<taux1>8.4427697009</taux1>
		<taux2>0.1184445431</taux2>
	</historique>

	<historique>
		<date>2009/01/18</date>
		<taux1>8.4479054860</taux1>
		<taux2>0.1183725364</taux2>
	</historique>

	<historique>
		<date>2009/01/19</date>
		<taux1>8.5495045488</taux1>
		<taux2>0.1169658422</taux2>
	</historique>

	<historique>
		<date>2009/01/20</date>
		<taux1>8.6718674262</taux1>
		<taux2>0.1153154160</taux2>
	</historique>

	<historique>
		<date>2009/01/21</date>
		<taux1>8.7142533940</taux1>
		<taux2>0.1147545240</taux2>
	</historique>

	<historique>
		<date>2009/01/22</date>
		<taux1>8.7763911249</taux1>
		<taux2>0.1139420504</taux2>
	</historique>

	<historique>
		<date>2009/01/23</date>
		<taux1>9.1495709539</taux1>
		<taux2>0.1092947423</taux2>
	</historique>

	<historique>
		<date>2009/01/24</date>
		<taux1>9.2186338354</taux1>
		<taux2>0.1084759432</taux2>
	</historique>

	<historique>
		<date>2009/01/25</date>
		<taux1>9.1996937156</taux1>
		<taux2>0.1086992710</taux2>
	</historique>

	<historique>
		<date>2009/01/26</date>
		<taux1>9.2081124810</taux1>
		<taux2>0.1085998897</taux2>
	</historique>

	<historique>
		<date>2009/01/27</date>
		<taux1>9.1217707123</taux1>
		<taux2>0.1096278378</taux2>
	</historique>

	<historique>
		<date>2009/01/28</date>
		<taux1>9.1522920203</taux1>
		<taux2>0.1092622479</taux2>
	</historique>

	<historique>
		<date>2009/01/29</date>
		<taux1>9.4167933798</taux1>
		<taux2>0.1061932613</taux2>
	</historique>

	<historique>
		<date>2009/01/30</date>
		<taux1>9.8178344864</taux1>
		<taux2>0.1018554551</taux2>
	</historique>

	<historique>
		<date>2009/01/31</date>
		<taux1>9.8179868116</taux1>
		<taux2>0.1018538749</taux2>
	</historique>

	<historique>
		<date>2009/02/01</date>
		<taux1>9.9025597590</taux1>
		<taux2>0.1009839904</taux2>
	</historique>

	<historique>
		<date>2009/02/02</date>
		<taux1>9.6880293155</taux1>
		<taux2>0.1032201666</taux2>
	</historique>

	<historique>
		<date>2009/02/03</date>
		<taux1>9.5264625853</taux1>
		<taux2>0.1049707581</taux2>
	</historique>

	<historique>
		<date>2009/02/04</date>
		<taux1>9.7596223393</taux1>
		<taux2>0.1024629812</taux2>
	</historique>

	<historique>
		<date>2009/02/05</date>
		<taux1>10.7985944640</taux1>
		<taux2>0.9920773250</taux2>
	</historique>

	<historique>
		<date>2009/02/06</date>
		<taux1>10.1434689344</taux1>
		<taux2>0.9858560290</taux2>
	</historique>

	<historique>
		<date>2009/02/07</date>
		<taux1>10.1200993316</taux1>
		<taux2>0.9881325940</taux2>
	</historique>

	<historique>
		<date>2009/02/08</date>
		<taux1>10.1426316234</taux1>
		<taux2>0.9859374150</taux2>
	</historique>

	<historique>
		<date>2009/02/09</date>
		<taux1>9.9003639050</taux1>
		<taux2>0.1010063882</taux2>
	</historique>

	<historique>
		<date>2009/02/10</date>
		<taux1>10.2455631830</taux1>
		<taux2>0.9760322420</taux2>
	</historique>

	<historique>
		<date>2009/02/11</date>
		<taux1>10.5153394850</taux1>
		<taux2>0.9509916460</taux2>
	</historique>

	<historique>
		<date>2009/02/12</date>
		<taux1>10.5856738852</taux1>
		<taux2>0.9446729710</taux2>
	</historique>

	<historique>
		<date>2009/02/13</date>
		<taux1>10.5929393399</taux1>
		<taux2>0.9440250420</taux2>
	</historique>

	<historique>
		<date>2009/02/14</date>
		<taux1>10.6227551744</taux1>
		<taux2>0.9413753620</taux2>
	</historique>

	<historique>
		<date>2009/02/15</date>
		<taux1>10.6642860014</taux1>
		<taux2>0.9377092850</taux2>
	</historique>

	<historique>
		<date>2009/02/16</date>
		<taux1>10.6642860014</taux1>
		<taux2>0.9377092850</taux2>
	</historique>

	<historique>
		<date>2009/02/17</date>
		<taux1>11.1349818539</taux1>
		<taux2>0.8980706150</taux2>
	</historique>

	<historique>
		<date>2009/02/18</date>
		<taux1>11.4181480044</taux1>
		<taux2>0.8757987720</taux2>
	</historique>

	<historique>
		<date>2009/02/19</date>
		<taux1>11.4080188120</taux1>
		<taux2>0.9057313140</taux2>
	</historique>

	<historique>
		<date>2009/02/20</date>
		<taux1>11.2507924930</taux1>
		<taux2>0.8888262770</taux2>
	</historique>

	<historique>
		<date>2009/02/21</date>
		<taux1>11.2561143517</taux1>
		<taux2>0.8884060420</taux2>
	</historique>

	<historique>
		<date>2009/02/22</date>
		<taux1>11.2914931656</taux1>
		<taux2>0.8856224640</taux2>
	</historique>

	<historique>
		<date>2009/02/23</date>
		<taux1>11.1349818539</taux1>
		<taux2>0.8980706150</taux2>
	</historique>

	<historique>
		<date>2009/02/24</date>
		<taux1>10.7892297651</taux1>
		<taux2>0.9268502220</taux2>
	</historique>

	<historique>
		<date>2009/02/25</date>
		<taux1>10.7750165235</taux1>
		<taux2>0.9280728230</taux2>
	</historique>

	<historique>
		<date>2009/02/26</date>
		<taux1>10.3218942011</taux1>
		<taux2>0.9688144250</taux2>
	</historique>

	<historique>
		<date>2009/02/27</date>
		<taux1>10.3309302928</taux1>
		<taux2>0.9679670380</taux2>
	</historique>

	<historique>
		<date>2009/02/28</date>
		<taux1>10.3490559097</taux1>
		<taux2>0.9662717150</taux2>
	</historique>

	<historique>
		<date>2009/03/01</date>
		<taux1>10.3893519454</taux1>
		<taux2>0.9625239430</taux2>
	</historique>

	<historique>
		<date>2009/03/02</date>
		<taux1>10.2773805167</taux1>
		<taux2>0.9730105820</taux2>
	</historique>

	<historique>
		<date>2009/03/03</date>
		<taux1>10.1820516652</taux1>
		<taux2>0.9821203360</taux2>
	</historique>

	<historique>
		<date>2009/03/04</date>
		<taux1>10.2463179917</taux1>
		<taux2>0.9759603410</taux2>
	</historique>

	<historique>
		<date>2009/03/05</date>
		<taux1>10.5770465840</taux1>
		<taux2>0.9454435050</taux2>
	</historique>

	<historique>
		<date>2009/03/06</date>
		<taux1>10.5242552135</taux1>
		<taux2>0.9501860030</taux2>
	</historique>

	<historique>
		<date>2009/03/07</date>
		<taux1>10.5527189552</taux1>
		<taux2>0.9476230760</taux2>
	</historique>

	<historique>
		<date>2009/03/08</date>
		<taux1>10.5510509749</taux1>
		<taux2>0.9477728830</taux2>
	</historique>

	<historique>
		<date>2009/03/09</date>
		<taux1>10.2523985058</taux1>
		<taux2>0.9753815160</taux2>
	</historique>

	<historique>
		<date>2009/03/10</date>
		<taux1>10.2050223460</taux1>
		<taux2>0.9979539710</taux2>
	</historique>

	<historique>
		<date>2009/03/11</date>
		<taux1>9.9830054688</taux1>
		<taux2>0.1001702346</taux2>
	</historique>

	<historique>
		<date>2009/03/12</date>
		<taux1>10.6020095200</taux1>
		<taux2>0.9940159290</taux2>
	</historique>

	<historique>
		<date>2009/03/13</date>
		<taux1>10.2387088815</taux1>
		<taux2>0.9766856460</taux2>
	</historique>

	<historique>
		<date>2009/03/14</date>
		<taux1>10.1867975090</taux1>
		<taux2>0.9816627840</taux2>
	</historique>

	<historique>
		<date>2009/03/15</date>
		<taux1>10.2266934726</taux1>
		<taux2>0.9778331610</taux2>
	</historique>

	<historique>
		<date>2009/03/16</date>
		<taux1>9.9558610404</taux1>
		<taux2>0.1004433465</taux2>
	</historique>

	<historique>
		<date>2009/03/17</date>
		<taux1>9.7683266323</taux1>
		<taux2>0.1023716792</taux2>
	</historique>

	<historique>
		<date>2009/03/18</date>
		<taux1>9.4436318745</taux1>
		<taux2>0.1058914635</taux2>
	</historique>

	<historique>
		<date>2009/03/19</date>
		<taux1>9.9063280537</taux1>
		<taux2>0.1009455769</taux2>
	</historique>

	<historique>
		<date>2009/03/21</date>
		<taux1>10.1726756433</taux1>
		<taux2>0.9830255430</taux2>
	</historique>

	<historique>
		<date>2009/03/22</date>
		<taux1>10.1632463825</taux1>
		<taux2>0.9839375750</taux2>
	</historique>

	<historique>
		<date>2009/03/23</date>
		<taux1>10.1648015102</taux1>
		<taux2>0.9837870410</taux2>
	</historique>

	<historique>
		<date>2009/03/24</date>
		<taux1>9.9824892193</taux1>
		<taux2>0.1001754150</taux2>
	</historique>

	<historique>
		<date>2009/03/25</date>
		<taux1>9.9566806655</taux1>
		<taux2>0.1004350781</taux2>
	</historique>

	<historique>
		<date>2009/03/26</date>
		<taux1>10.7798507180</taux1>
		<taux2>0.9922618390</taux2>
	</historique>

	<historique>
		<date>2009/03/27</date>
		<taux1>10.3512381330</taux1>
		<taux2>0.9964999120</taux2>
	</historique>

	<historique>
		<date>2009/03/28</date>
		<taux1>10.3833126360</taux1>
		<taux2>0.9961815100</taux2>
	</historique>

	<historique>
		<date>2009/03/29</date>
		<taux1>10.3427543070</taux1>
		<taux2>0.9965841650</taux2>
	</historique>

	<historique>
		<date>2009/03/30</date>
		<taux1>9.9128024222</taux1>
		<taux2>0.1008796461</taux2>
	</historique>

	<historique>
		<date>2009/03/31</date>
		<taux1>9.7561154990</taux1>
		<taux2>0.1024998115</taux2>
	</historique>

	<historique>
		<date>2009/04/01</date>
		<taux1>9.8431018337</taux1>
		<taux2>0.1015939911</taux2>
	</historique>

	<historique>
		<date>2009/04/02</date>
		<taux1>9.6552460417</taux1>
		<taux2>0.1035706388</taux2>
	</historique>

	<historique>
		<date>2009/04/03</date>
		<taux1>9.4506388922</taux1>
		<taux2>0.1058129521</taux2>
	</historique>

	<historique>
		<date>2009/04/04</date>
		<taux1>9.4256089283</taux1>
		<taux2>0.1060939413</taux2>
	</historique>

	<historique>
		<date>2009/04/05</date>
		<taux1>9.4569248317</taux1>
		<taux2>0.1057426191</taux2>
	</historique>

	<historique>
		<date>2009/04/06</date>
		<taux1>9.8031796940</taux1>
		<taux2>0.1101283020</taux2>
	</historique>

	<historique>
		<date>2009/04/07</date>
		<taux1>9.2790130476</taux1>
		<taux2>0.1077700823</taux2>
	</historique>

	<historique>
		<date>2009/04/08</date>
		<taux1>9.2956830244</taux1>
		<taux2>0.1075768179</taux2>
	</historique>

	<historique>
		<date>2009/04/09</date>
		<taux1>9.3794050682</taux1>
		<taux2>0.1066165703</taux2>
	</historique>

	<historique>
		<date>2009/04/10</date>
		<taux1>9.4072554017</taux1>
		<taux2>0.1063009302</taux2>
	</historique>

	<historique>
		<date>2009/04/11</date>
		<taux1>9.3789957632</taux1>
		<taux2>0.1066212231</taux2>
	</historique>

	<historique>
		<date>2009/04/12</date>
		<taux1>9.3901315370</taux1>
		<taux2>0.1064947808</taux2>
	</historique>

	<historique>
		<date>2009/04/13</date>
		<taux1>9.5221644865</taux1>
		<taux2>0.1050181397</taux2>
	</historique>

	<historique>
		<date>2009/04/14</date>
		<taux1>9.5831344602</taux1>
		<taux2>0.1043499916</taux2>
	</historique>

	<historique>
		<date>2009/04/16</date>
		<taux1>9.2665878455</taux1>
		<taux2>0.1079145870</taux2>
	</historique>

	<historique>
		<date>2009/04/17</date>
		<taux1>9.1252675108</taux1>
		<taux2>0.1095858285</taux2>
	</historique>

	<historique>
		<date>2009/04/18</date>
		<taux1>9.0672012683</taux1>
		<taux2>0.1102876147</taux2>
	</historique>

	<historique>
		<date>2009/04/19</date>
		<taux1>9.0951616357</taux1>
		<taux2>0.1099485683</taux2>
	</historique>

	<historique>
		<date>2009/04/20</date>
		<taux1>9.3544738713</taux1>
		<taux2>0.1069007208</taux2>
	</historique>

	<historique>
		<date>2009/04/21</date>
		<taux1>9.2523499856</taux1>
		<taux2>0.1080806499</taux2>
	</historique>

	<historique>
		<date>2009/04/22</date>
		<taux1>9.4677302548</taux1>
		<taux2>0.1056219361</taux2>
	</historique>

	<historique>
		<date>2009/04/23</date>
		<taux1>9.7735222452</taux1>
		<taux2>0.1023172583</taux2>
	</historique>

	<historique>
		<date>2009/04/24</date>
		<taux1>9.7203327327</taux1>
		<taux2>0.1028771368</taux2>
	</historique>

	<historique>
		<date>2009/04/25</date>
		<taux1>9.7341408391</taux1>
		<taux2>0.1027312031</taux2>
	</historique>

	<historique>
		<date>2009/04/26</date>
		<taux1>9.6986594174</taux1>
		<taux2>0.1031070333</taux2>
	</historique>

	<historique>
		<date>2009/04/27</date>
		<taux1>9.8717665887</taux1>
		<taux2>0.1012989915</taux2>
	</historique>

	<historique>
		<date>2009/04/28</date>
		<taux1>9.5132451934</taux1>
		<taux2>0.1051166011</taux2>
	</historique>

	<historique>
		<date>2009/04/29</date>
		<taux1>9.6320818124</taux1>
		<taux2>0.1038197162</taux2>
	</historique>

	<historique>
		<date>2009/04/30</date>
		<taux1>9.3672507040</taux1>
		<taux2>0.1067549094</taux2>
	</historique>

	<historique>
		<date>2009/05/01</date>
		<taux1>9.3780148646</taux1>
		<taux2>0.1066323752</taux2>
	</historique>

	<historique>
		<date>2009/05/02</date>
		<taux1>9.4203292112</taux1>
		<taux2>0.1061534027</taux2>
	</historique>

	<historique>
		<date>2009/05/03</date>
		<taux1>9.3927841614</taux1>
		<taux2>0.1064647055</taux2>
	</historique>

	<historique>
		<date>2009/05/04</date>
		<taux1>9.7422994560</taux1>
		<taux2>0.1026451717</taux2>
	</historique>

	<historique>
		<date>2009/05/05</date>
		<taux1>10.0478163450</taux1>
		<taux2>0.0995241121</taux2>
	</historique>

	<historique>
		<date>2009/05/06</date>
		<taux1>10.2949665591</taux1>
		<taux2>0.0971348468</taux2>
	</historique>

	<historique>
		<date>2009/05/07</date>
		<taux1>10.3573823319</taux1>
		<taux2>0.0965494917</taux2>
	</historique>

	<historique>
		<date>2009/05/08</date>
		<taux1>10.2784930172</taux1>
		<taux2>0.0972905268</taux2>
	</historique>

	<historique>
		<date>2009/05/09</date>
		<taux1>10.4603924415</taux1>
		<taux2>0.0955987078</taux2>
	</historique>

	<historique>
		<date>2009/05/10</date>
		<taux1>10.2806286033</taux1>
		<taux2>0.0972703167</taux2>
	</historique>

	<historique>
		<date>2009/05/11</date>
		<taux1>10.2591937668</taux1>
		<taux2>0.0974735464</taux2>
	</historique>

	<historique>
		<date>2009/05/12</date>
		<taux1>10.4405427251</taux1>
		<taux2>0.0957804615</taux2>
	</historique>

	<historique>
		<date>2009/05/13</date>
		<taux1>10.2971584693</taux1>
		<taux2>0.0971141702</taux2>
	</historique>

	<historique>
		<date>2009/05/14</date>
		<taux1>10.2705484417</taux1>
		<taux2>0.0973657839</taux2>
	</historique>

	<historique>
		<date>2009/05/15</date>
		<taux1>10.3652991305</taux1>
		<taux2>0.0964757493</taux2>
	</historique>

	<historique>
		<date>2009/05/16</date>
		<taux1>10.3061113422</taux1>
		<taux2>0.0970298075</taux2>
	</historique>

	<historique>
		<date>2009/05/17</date>
		<taux1>10.3381582577</taux1>
		<taux2>0.0967290280</taux2>
	</historique>

	<historique>
		<date>2009/05/18</date>
		<taux1>10.2204382093</taux1>
		<taux2>0.0978431628</taux2>
	</historique>

	<historique>
		<date>2009/05/19</date>
		<taux1>10.3887445740</taux1>
		<taux2>0.0962580216</taux2>
	</historique>

	<historique>
		<date>2009/05/20</date>
		<taux1>10.3736131534</taux1>
		<taux2>0.0963984279</taux2>
	</historique>

	<historique>
		<date>2009/05/21</date>
		<taux1>10.4554079386</taux1>
		<taux2>0.0956442834</taux2>
	</historique>

	<historique>
		<date>2009/05/22</date>
		<taux1>10.4750065187</taux1>
		<taux2>0.0954653344</taux2>
	</historique>

	<historique>
		<date>2009/05/23</date>
		<taux1>10.4513439516</taux1>
		<taux2>0.0956814745</taux2>
	</historique>

	<historique>
		<date>2009/05/24</date>
		<taux1>10.4549413660</taux1>
		<taux2>0.0956485517</taux2>
	</historique>

	<historique>
		<date>2009/05/25</date>
		<taux1>10.5314205044</taux1>
		<taux2>0.0949539523</taux2>
	</historique>

	<historique>
		<date>2009/05/26</date>
		<taux1>10.4384338663</taux1>
		<taux2>0.0957998118</taux2>
	</historique>

	<historique>
		<date>2009/05/27</date>
		<taux1>10.6434626021</taux1>
		<taux2>0.0939543866</taux2>
	</historique>

	<historique>
		<date>2009/05/28</date>
		<taux1>10.8664643147</taux1>
		<taux2>0.0920262535</taux2>
	</historique>

	<historique>
		<date>2009/05/29</date>
		<taux1>11.0577484097</taux1>
		<taux2>0.0904343238</taux2>
	</historique>

	<historique>
		<date>2009/05/30</date>
		<taux1>11.1625351111</taux1>
		<taux2>0.0895853845</taux2>
	</historique>

	<historique>
		<date>2009/05/31</date>
		<taux1>11.1413454225</taux1>
		<taux2>0.0897557667</taux2>
	</historique>

	<historique>
		<date>2009/06/01</date>
		<taux1>11.0361791551</taux1>
		<taux2>0.0906110698</taux2>
	</historique>

	<historique>
		<date>2009/06/02</date>
		<taux1>11.1317809651</taux1>
		<taux2>0.0898328851</taux2>
	</historique>

	<historique>
		<date>2009/06/03</date>
		<taux1>10.8013393593</taux1>
		<taux2>0.0925811112</taux2>
	</historique>

	<historique>
		<date>2009/06/04</date>
		<taux1>11.2010591079</taux1>
		<taux2>0.0892772719</taux2>
	</historique>

	<historique>
		<date>2009/06/05</date>
		<taux1>10.9271562179</taux1>
		<taux2>0.0915151189</taux2>
	</historique>

	<historique>
		<date>2009/06/05</date>
		<taux1>9.6210305698</taux1>
		<taux2>0.1039389692</taux2>
	</historique>

	<historique>
		<date>2009/06/06</date>
		<taux1>10.9381877418</taux1>
		<taux2>0.0914228228</taux2>
	</historique>

	<historique>
		<date>2009/06/07</date>
		<taux1>10.9416396899</taux1>
		<taux2>0.0913939801</taux2>
	</historique>

	<historique>
		<date>2009/06/08</date>
		<taux1>10.7571646589</taux1>
		<taux2>0.0929612990</taux2>
	</historique>

	<historique>
		<date>2009/06/09</date>
		<taux1>10.8201254949</taux1>
		<taux2>0.0924203698</taux2>
	</historique>

	<historique>
		<date>2009/06/10</date>
		<taux1>10.8428057153</taux1>
		<taux2>0.0922270514</taux2>
	</historique>

	<historique>
		<date>2009/06/11</date>
		<taux1>10.8973348781</taux1>
		<taux2>0.0917655566</taux2>
	</historique>

	<historique>
		<date>2009/06/12</date>
		<taux1>10.2341112299</taux1>
		<taux2>0.0977124420</taux2>
	</historique>

	<historique>
		<date>2009/06/12</date>
		<taux1>10.6277563985</taux1>
		<taux2>0.0940932369</taux2>
	</historique>

	<historique>
		<date>2009/06/13</date>
		<taux1>10.5897812930</taux1>
		<taux2>0.0944306565</taux2>
	</historique>

	<historique>
		<date>2009/06/14</date>
		<taux1>10.5537321665</taux1>
		<taux2>0.0947532100</taux2>
	</historique>

	<historique>
		<date>2009/06/15</date>
		<taux1>10.2297777755</taux1>
		<taux2>0.0977538341</taux2>
	</historique>

	<historique>
		<date>2009/06/16</date>
		<taux1>10.2283753503</taux1>
		<taux2>0.0977672373</taux2>
	</historique>

	<historique>
		<date>2009/06/17</date>
		<taux1>10.2734083741</taux1>
		<taux2>0.0973386790</taux2>
	</historique>

	<historique>
		<date>2009/06/18</date>
		<taux1>10.2059736181</taux1>
		<taux2>0.0979818327</taux2>
	</historique>

	<historique>
		<date>2009/06/19</date>
		<taux1>10.1725934953</taux1>
		<taux2>0.0983033482</taux2>
	</historique>

	<historique>
		<date>2009/06/20</date>
		<taux1>10.1818960047</taux1>
		<taux2>0.0982135350</taux2>
	</historique>

	<historique>
		<date>2009/06/21</date>
		<taux1>10.1764248836</taux1>
		<taux2>0.0982663373</taux2>
	</historique>

	<historique>
		<date>2009/06/22</date>
		<taux1>9.9207128321</taux1>
		<taux2>0.1007992084</taux2>
	</historique>

	<historique>
		<date>2009/06/23</date>
		<taux1>9.8473769562</taux1>
		<taux2>0.1015498853</taux2>
	</historique>

	<historique>
		<date>2009/06/24</date>
		<taux1>9.9399208945</taux1>
		<taux2>0.1006044224</taux2>
	</historique>

	<historique>
		<date>2009/06/25</date>
		<taux1>9.9399208945</taux1>
		<taux2>0.1006044224</taux2>
	</historique>

	<historique>
		<date>2009/06/26</date>
		<taux1>10.0134784942</taux1>
		<taux2>0.0998653965</taux2>
	</historique>

	<historique>
		<date>2009/06/27</date>
		<taux1>10.0099605829</taux1>
		<taux2>0.0999004933</taux2>
	</historique>

	<historique>
		<date>2009/06/28</date>
		<taux1>10.0037961345</taux1>
		<taux2>0.0999620531</taux2>
	</historique>

	<historique>
		<date>2009/06/29</date>
		<taux1>9.8773305810</taux1>
		<taux2>0.1012419289</taux2>
	</historique>

	<historique>
		<date>2009/06/30</date>
		<taux1>9.7012514692</taux1>
		<taux2>0.1030794845</taux2>
	</historique>

	<historique>
		<date>2009/07/01</date>
		<taux1>9.7126675636</taux1>
		<taux2>0.1029583267</taux2>
	</historique>

	<historique>
		<date>2009/07/02</date>
		<taux1>9.5314511487</taux1>
		<taux2>0.1049158186</taux2>
	</historique>

	<historique>
		<date>2009/07/03</date>
		<taux1>9.6069224743</taux1>
		<taux2>0.1040916071</taux2>
	</historique>

	<historique>
		<date>2009/07/04</date>
		<taux1>9.5717747954</taux1>
		<taux2>0.1044738328</taux2>
	</historique>

	<historique>
		<date>2009/07/06</date>
		<taux1>9.4915643279</taux1>
		<taux2>0.1053567110</taux2>
	</historique>

	<historique>
		<date>2009/07/07</date>
		<taux1>9.4310725548</taux1>
		<taux2>0.1060324787</taux2>
	</historique>

	<historique>
		<date>2009/07/08</date>
		<taux1>9.2499064867</taux1>
		<taux2>0.1081092010</taux2>
	</historique>

	<historique>
		<date>2009/07/09</date>
		<taux1>9.1732274060</taux1>
		<taux2>0.1090128867</taux2>
	</historique>

	<historique>
		<date>2009/07/10</date>
		<taux1>9.0602009787</taux1>
		<taux2>0.1103728275</taux2>
	</historique>

	<historique>
		<date>2009/07/11</date>
		<taux1>9.1063443832</taux1>
		<taux2>0.1098135495</taux2>
	</historique>

	<historique>
		<date>2009/07/12</date>
		<taux1>9.1169316193</taux1>
		<taux2>0.1096860261</taux2>
	</historique>

	<historique>
		<date>2009/07/13</date>
		<taux1>9.1340916712</taux1>
		<taux2>0.1094799610</taux2>
	</historique>

	<historique>
		<date>2009/07/14</date>
		<taux1>9.2458803807</taux1>
		<taux2>0.1081562770</taux2>
	</historique>

	<historique>
		<date>2009/07/15</date>
		<taux1>9.4005737266</taux1>
		<taux2>0.1063764861</taux2>
	</historique>

	<historique>
		<date>2009/07/16</date>
		<taux1>9.3878011057</taux1>
		<taux2>0.1065212171</taux2>
	</historique>

	<historique>
		<date>2009/07/17</date>
		<taux1>9.4795923155</taux1>
		<taux2>0.1054897686</taux2>
	</historique>

	<historique>
		<date>2009/07/18</date>
		<taux1>9.5238847164</taux1>
		<taux2>0.1049991710</taux2>
	</historique>

	<historique>
		<date>2009/07/19</date>
		<taux1>9.5189150044</taux1>
		<taux2>0.1050539898</taux2>
	</historique>

	<historique>
		<date>2009/07/21</date>
		<taux1>9.5563472990</taux1>
		<taux2>0.1046424924</taux2>
	</historique>

	<historique>
		<date>2009/07/22</date>
		<taux1>9.6087814949</taux1>
		<taux2>0.1040714684</taux2>
	</historique>

	<historique>
		<date>2009/07/23</date>
		<taux1>9.7009195094</taux1>
		<taux2>0.1030830118</taux2>
	</historique>

	<historique>
		<date>2009/07/24</date>
		<taux1>9.7414018491</taux1>
		<taux2>0.1026546297</taux2>
	</historique>

	<historique>
		<date>2009/07/25</date>
		<taux1>9.7578142972</taux1>
		<taux2>0.1024819667</taux2>
	</historique>

	<historique>
		<date>2009/07/26</date>
		<taux1>9.7830963144</taux1>
		<taux2>0.1022171272</taux2>
	</historique>

	<historique>
		<date>2009/07/27</date>
		<taux1>9.8638557833</taux1>
		<taux2>0.1013802332</taux2>
	</historique>

	<historique>
		<date>2009/07/28</date>
		<taux1>9.6896260370</taux1>
		<taux2>0.1032031573</taux2>
	</historique>

	<historique>
		<date>2009/07/29</date>
		<taux1>9.4756944292</taux1>
		<taux2>0.1055331625</taux2>
	</historique>

	<historique>
		<date>2009/07/30</date>
		<taux1>9.5967724680</taux1>
		<taux2>0.1042016994</taux2>
	</historique>

	<historique>
		<date>2009/07/31</date>
		<taux1>9.7441327883</taux1>
		<taux2>0.1026258592</taux2>
	</historique>

	<historique>
		<date>2009/08/01</date>
		<taux1>9.8245733213</taux1>
		<taux2>0.1017855908</taux2>
	</historique>

	<historique>
		<date>2009/08/02</date>
		<taux1>9.7505157135</taux1>
		<taux2>0.1025586779</taux2>
	</historique>

	<historique>
		<date>2009/08/03</date>
		<taux1>9.8895260410</taux1>
		<taux2>0.1011170804</taux2>
	</historique>

	<historique>
		<date>2009/08/04</date>
		<taux1>10.1239358394</taux1>
		<taux2>0.0987758137</taux2>
	</historique>

	<historique>
		<date>2009/08/05</date>
		<taux1>10.2324506963</taux1>
		<taux2>0.0977282989</taux2>
	</historique>

	<historique>
		<date>2009/08/06</date>
		<taux1>10.1719235071</taux1>
		<taux2>0.0983098230</taux2>
	</historique>

	<historique>
		<date>2009/08/07</date>
		<taux1>10.2849569369</taux1>
		<taux2>0.0972293813</taux2>
	</historique>

	<historique>
		<date>2009/08/08</date>
		<taux1>10.2840629823</taux1>
		<taux2>0.0972378331</taux2>
	</historique>

	<historique>
		<date>2009/08/09</date>
		<taux1>10.3122283015</taux1>
		<taux2>0.0969722519</taux2>
	</historique>

	<historique>
		<date>2009/08/10</date>
		<taux1>10.1618909670</taux1>
		<taux2>0.0984068815</taux2>
	</historique>

	<historique>
		<date>2009/08/11</date>
		<taux1>10.1482915079</taux1>
		<taux2>0.0985387540</taux2>
	</historique>

	<historique>
		<date>2009/08/13</date>
		<taux1>10.4966900268</taux1>
		<taux2>0.0952681271</taux2>
	</historique>

	<historique>
		<date>2009/08/14</date>
		<taux1>10.3665597599</taux1>
		<taux2>0.0964640173</taux2>
	</historique>

	<historique>
		<date>2009/08/15</date>
		<taux1>10.2700442466</taux1>
		<taux2>0.0973705639</taux2>
	</historique>

	<historique>
		<date>2009/08/16</date>
		<taux1>10.3447012375</taux1>
		<taux2>0.0966678473</taux2>
	</historique>

	<historique>
		<date>2009/08/17</date>
		<taux1>9.9762855299</taux1>
		<taux2>0.1002377084</taux2>
	</historique>

	<historique>
		<date>2009/08/18</date>
		<taux1>9.8946944675</taux1>
		<taux2>0.1010642626</taux2>
	</historique>

	<historique>
		<date>2009/08/19</date>
		<taux1>9.6962332064</taux1>
		<taux2>0.1031328330</taux2>
	</historique>

	<historique>
		<date>2009/08/20</date>
		<taux1>9.7523384484</taux1>
		<taux2>0.1025395094</taux2>
	</historique>

	<historique>
		<date>2009/08/21</date>
		<taux1>9.8927153276</taux1>
		<taux2>0.1010844815</taux2>
	</historique>

	<historique>
		<date>2009/08/22</date>
		<taux1>9.9093230109</taux1>
		<taux2>0.1009150674</taux2>
	</historique>

	<historique>
		<date>2009/08/23</date>
		<taux1>9.9049762987</taux1>
		<taux2>0.1009593531</taux2>
	</historique>

	<historique>
		<date>2009/08/24</date>
		<taux1>9.8800279526</taux1>
		<taux2>0.1012142885</taux2>
	</historique>

	<historique>
		<date>2009/08/25</date>
		<taux1>9.9922830202</taux1>
		<taux2>0.1000772294</taux2>
	</historique>

	<historique>
		<date>2009/08/26</date>
		<taux1>10.0282526484</taux1>
		<taux2>0.0997182695</taux2>
	</historique>

	<historique>
		<date>2009/08/27</date>
		<taux1>9.9382150592</taux1>
		<taux2>0.1006216905</taux2>
	</historique>

	<historique>
		<date>2009/08/27</date>
		<taux1>9.9382150592</taux1>
		<taux2>0.1006216905</taux2>
	</historique>

	<historique>
		<date>2009/08/28</date>
		<taux1>10.3270011724</taux1>
		<taux2>0.0968335321</taux2>
	</historique>

	<historique>
		<date>2009/08/29</date>
		<taux1>10.3058904185</taux1>
		<taux2>0.0970318875</taux2>
	</historique>

	<historique>
		<date>2009/08/30</date>
		<taux1>10.3402953463</taux1>
		<taux2>0.0967090365</taux2>
	</historique>

	<historique>
		<date>2009/08/31</date>
		<taux1>10.3939305226</taux1>
		<taux2>0.0962099947</taux2>
	</historique>

	<historique>
		<date>2009/09/01</date>
		<taux1>10.5477904593</taux1>
		<taux2>0.0948065857</taux2>
	</historique>

	<historique>
		<date>2009/09/02</date>
		<taux1>10.7680918224</taux1>
		<taux2>0.0928669644</taux2>
	</historique>

	<historique>
		<date>2009/09/03</date>
		<taux1>11.2792676496</taux1>
		<taux2>0.0886582384</taux2>
	</historique>

	<historique>
		<date>2009/09/04</date>
		<taux1>11.3122020926</taux1>
		<taux2>0.0884001180</taux2>
	</historique>

	<historique>
		<date>2009/09/05</date>
		<taux1>11.3589178975</taux1>
		<taux2>0.0880365550</taux2>
	</historique>

	<historique>
		<date>2009/09/06</date>
		<taux1>11.3661343977</taux1>
		<taux2>0.0879806595</taux2>
	</historique>

	<historique>
		<date>2009/09/07</date>
		<taux1>11.3648262664</taux1>
		<taux2>0.0879907864</taux2>
	</historique>

	<historique>
		<date>2009/09/08</date>
		<taux1>11.3545167081</taux1>
		<taux2>0.0880706793</taux2>
	</historique>

	<historique>
		<date>2009/09/09</date>
		<taux1>11.2213998144</taux1>
		<taux2>0.0891154416</taux2>
	</historique>

	<historique>
		<date>2009/09/10</date>
		<taux1>11.3956502424</taux1>
		<taux2>0.0877527810</taux2>
	</historique>

	<historique>
		<date>2009/09/11</date>
		<taux1>11.5066405471</taux1>
		<taux2>0.0869063386</taux2>
	</historique>

	<historique>
		<date>2009/09/12</date>
		<taux1>11.4978283439</taux1>
		<taux2>0.0869729457</taux2>
	</historique>

	<historique>
		<date>2009/09/13</date>
		<taux1>11.4909894367</taux1>
		<taux2>0.0870247080</taux2>
	</historique>

	<historique>
		<date>2009/09/14</date>
		<taux1>11.3264658382</taux1>
		<taux2>0.0882887932</taux2>
	</historique>

	<historique>
		<date>2009/09/15</date>
		<taux1>11.5614128451</taux1>
		<taux2>0.0864946191</taux2>
	</historique>

	<historique>
		<date>2009/09/16</date>
		<taux1>11.7954066000</taux1>
		<taux2>0.0847787646</taux2>
	</historique>

	<historique>
		<date>2009/09/17</date>
		<taux1>11.7442606730</taux1>
		<taux2>0.0851479738</taux2>
	</historique>

	<historique>
		<date>2009/09/18</date>
		<taux1>11.5605535117</taux1>
		<taux2>0.0865010485</taux2>
	</historique>

	<historique>
		<date>2009/09/19</date>
		<taux1>11.5285593777</taux1>
		<taux2>0.0867411068</taux2>
	</historique>

	<historique>
		<date>2009/09/20</date>
		<taux1>11.5278568099</taux1>
		<taux2>0.0867463932</taux2>
	</historique>

	<historique>
		<date>2009/09/21</date>
		<taux1>11.4777954848</taux1>
		<taux2>0.0871247446</taux2>
	</historique>

	<historique>
		<date>2009/09/22</date>
		<taux1>11.5473728018</taux1>
		<taux2>0.0865997848</taux2>
	</historique>

	<historique>
		<date>2009/09/23</date>
		<taux1>11.4631202418</taux1>
		<taux2>0.0872362829</taux2>
	</historique>

	<historique>
		<date>2009/09/28</date>
		<taux1>11.0725491442</taux1>
		<taux2>0.0903134397</taux2>
	</historique>

	<historique>
		<date>2009/10/07</date>
		<taux1>11.8973305939</taux1>
		<taux2>0.0840524681</taux2>
	</historique>

	<historique>
		<date>2009/10/08</date>
		<taux1>12.0190684387</taux1>
		<taux2>0.0832011237</taux2>
	</historique>

	<historique>
		<date>2009/10/09</date>
		<taux1>12.0227848280</taux1>
		<taux2>0.0831754052</taux2>
	</historique>

	<historique>
		<date>2009/10/10</date>
		<taux1>12.0135052960</taux1>
		<taux2>0.0832396520</taux2>
	</historique>

	<historique>
		<date>2009/10/11</date>
		<taux1>12.0369451341</taux1>
		<taux2>0.0830775574</taux2>
	</historique>

	<historique>
		<date>2009/10/12</date>
		<taux1>12.0091035220</taux1>
		<taux2>0.0832701624</taux2>
	</historique>

	<historique>
		<date>2009/10/13</date>
		<taux1>11.9855511000</taux1>
		<taux2>0.0834337939</taux2>
	</historique>

	<historique>
		<date>2009/10/14</date>
		<taux1>11.9877070426</taux1>
		<taux2>0.0834187886</taux2>
	</historique>

	<historique>
		<date>2009/10/15</date>
		<taux1>11.6640668896</taux1>
		<taux2>0.0857333904</taux2>
	</historique>

	<historique>
		<date>2009/10/16</date>
		<taux1>11.7138510061</taux1>
		<taux2>0.0853690216</taux2>
	</historique>

	<historique>
		<date>2009/10/17</date>
		<taux1>11.7089334432</taux1>
		<taux2>0.0854048752</taux2>
	</historique>

	<historique>
		<date>2009/10/18</date>
		<taux1>11.7040999429</taux1>
		<taux2>0.0854401453</taux2>
	</historique>

	<historique>
		<date>2009/10/19</date>
		<taux1>11.8621916461</taux1>
		<taux2>0.0843014537</taux2>
	</historique>

	<historique>
		<date>2009/10/20</date>
		<taux1>11.7723306643</taux1>
		<taux2>0.0849449466</taux2>
	</historique>

	<historique>
		<date>2009/10/21</date>
		<taux1>11.8255858149</taux1>
		<taux2>0.0845624069</taux2>
	</historique>

	<historique>
		<date>2009/10/22</date>
		<taux1>11.7203735755</taux1>
		<taux2>0.0853215125</taux2>
	</historique>

	<historique>
		<date>2009/10/23</date>
		<taux1>11.7773892697</taux1>
		<taux2>0.0849084612</taux2>
	</historique>

	<historique>
		<date>2009/10/24</date>
		<taux1>11.7576336850</taux1>
		<taux2>0.0850511274</taux2>
	</historique>

	<historique>
		<date>2009/10/25</date>
		<taux1>11.8063188265</taux1>
		<taux2>0.0847004062</taux2>
	</historique>

	<historique>
		<date>2009/10/26</date>
		<taux1>11.5210785296</taux1>
		<taux2>0.0867974294</taux2>
	</historique>

	<historique>
		<date>2009/10/27</date>
		<taux1>11.2416649105</taux1>
		<taux2>0.0889547952</taux2>
	</historique>

	<historique>
		<date>2009/10/28</date>
		<taux1>10.9933264388</taux1>
		<taux2>0.0909642778</taux2>
	</historique>

	<historique>
		<date>2009/10/29</date>
		<taux1>11.2293601187</taux1>
		<taux2>0.0890522692</taux2>
	</historique>

	<historique>
		<date>2009/10/30</date>
		<taux1>11.0644744492</taux1>
		<taux2>0.0903793492</taux2>
	</historique>

	<historique>
		<date>2009/10/31</date>
		<taux1>10.9932435525</taux1>
		<taux2>0.0909649636</taux2>
	</historique>

	<historique>
		<date>2009/11/01</date>
		<taux1>11.0742897707</taux1>
		<taux2>0.0902992445</taux2>
	</historique>

	<historique>
		<date>2009/11/02</date>
		<taux1>11.1192376673</taux1>
		<taux2>0.0899342230</taux2>
	</historique>

	<historique>
		<date>2009/11/03</date>
		<taux1>11.6848905976</taux1>
		<taux2>0.0855806044</taux2>
	</historique>

	<historique>
		<date>2009/11/04</date>
		<taux1>11.7632082561</taux1>
		<taux2>0.0850108217</taux2>
	</historique>

	<historique>
		<date>2009/11/05</date>
		<taux1>11.6985377890</taux1>
		<taux2>0.0854807685</taux2>
	</historique>

	<historique>
		<date>2009/11/06</date>
		<taux1>11.6891792836</taux1>
		<taux2>0.0855492054</taux2>
	</historique>

	<historique>
		<date>2009/11/07</date>
		<taux1>11.6895635016</taux1>
		<taux2>0.0855463936</taux2>
	</historique>

	<historique>
		<date>2009/11/08</date>
		<taux1>11.6840061710</taux1>
		<taux2>0.0855870825</taux2>
	</historique>

	<historique>
		<date>2009/11/09</date>
		<taux1>11.7195706245</taux1>
		<taux2>0.0853273581</taux2>
	</historique>

	<historique>
		<date>2009/11/10</date>
		<taux1>11.5532747295</taux1>
		<taux2>0.0865555458</taux2>
	</historique>

	<historique>
		<date>2009/11/11</date>
		<taux1>11.7205719784</taux1>
		<taux2>0.0853200682</taux2>
	</historique>

	<historique>
		<date>2009/11/12</date>
		<taux1>11.6422885995</taux1>
		<taux2>0.0858937649</taux2>
	</historique>

	<historique>
		<date>2009/11/13</date>
		<taux1>11.6605964222</taux1>
		<taux2>0.0857589066</taux2>
	</historique>

	<historique>
		<date>2009/11/14</date>
		<taux1>11.6689008288</taux1>
		<taux2>0.0856978746</taux2>
	</historique>

	<historique>
		<date>2009/11/15</date>
		<taux1>11.6764614176</taux1>
		<taux2>0.0856423846</taux2>
	</historique>

	<historique>
		<date>2009/11/16</date>
		<taux1>12.2696487223</taux1>
		<taux2>0.0815019258</taux2>
	</historique>

	<historique>
		<date>2009/11/17</date>
		<taux1>12.3560546862</taux1>
		<taux2>0.0809319824</taux2>
	</historique>

	<historique>
		<date>2009/11/18</date>
		<taux1>12.3740281301</taux1>
		<taux2>0.0808144276</taux2>
	</historique>

	<historique>
		<date>2009/11/19</date>
		<taux1>12.4279234800</taux1>
		<taux2>0.0804639650</taux2>
	</historique>

	<historique>
		<date>2009/11/20</date>
		<taux1>12.4395017496</taux1>
		<taux2>0.0803890719</taux2>
	</historique>

	<historique>
		<date>2009/11/21</date>
		<taux1>12.4226109066</taux1>
		<taux2>0.0804983757</taux2>
	</historique>

	<historique>
		<date>2009/11/22</date>
		<taux1>12.4480457687</taux1>
		<taux2>0.0803338949</taux2>
	</historique>

	<historique>
		<date>2009/11/23</date>
		<taux1>12.4289329051</taux1>
		<taux2>0.0804574301</taux2>
	</historique>

	<historique>
		<date>2009/11/24</date>
		<taux1>12.3948404614</taux1>
		<taux2>0.0806787311</taux2>
	</historique>

	<historique>
		<date>2009/11/25</date>
		<taux1>12.4552321352</taux1>
		<taux2>0.0802875442</taux2>
	</historique>

	<historique>
		<date>2009/11/26</date>
		<taux1>12.4168957662</taux1>
		<taux2>0.0805354268</taux2>
	</historique>

	<historique>
		<date>2009/11/27</date>
		<taux1>12.2372610350</taux1>
		<taux2>0.0817176325</taux2>
	</historique>

	<historique>
		<date>2009/11/28</date>
		<taux1>12.1991974410</taux1>
		<taux2>0.0819726056</taux2>
	</historique>

	<historique>
		<date>2009/11/29</date>
		<taux1>12.1858673326</taux1>
		<taux2>0.0820622753</taux2>
	</historique>

	<historique>
		<date>2009/11/30</date>
		<taux1>12.2743414087</taux1>
		<taux2>0.0814707663</taux2>
	</historique>

	<historique>
		<date>2009/12/01</date>
		<taux1>12.6450311696</taux1>
		<taux2>0.0790824464</taux2>
	</historique>

	<historique>
		<date>2009/12/02</date>
		<taux1>12.7839229806</taux1>
		<taux2>0.0782232497</taux2>
	</historique>

	<historique>
		<date>2009/12/03</date>
		<taux1>12.6536791199</taux1>
		<taux2>0.0790283988</taux2>
	</historique>

	<historique>
		<date>2009/12/04</date>
		<taux1>12.4258369955</taux1>
		<taux2>0.0804774761</taux2>
	</historique>

	<historique>
		<date>2009/12/05</date>
		<taux1>12.4415117933</taux1>
		<taux2>0.0803760842</taux2>
	</historique>

	<historique>
		<date>2009/12/06</date>
		<taux1>12.4412965774</taux1>
		<taux2>0.0803774746</taux2>
	</historique>

	<historique>
		<date>2009/12/07</date>
		<taux1>12.2799528103</taux1>
		<taux2>0.0814335377</taux2>
	</historique>

	<historique>
		<date>2009/12/08</date>
		<taux1>11.9455852624</taux1>
		<taux2>0.0837129348</taux2>
	</historique>

	<historique>
		<date>2009/12/09</date>
		<taux1>11.8109735696</taux1>
		<taux2>0.0846670255</taux2>
	</historique>

	<historique>
		<date>2009/12/10</date>
		<taux1>11.8055035060</taux1>
		<taux2>0.0847062558</taux2>
	</historique>

	<historique>
		<date>2009/12/11</date>
		<taux1>11.7402983836</taux1>
		<taux2>0.0851767108</taux2>
	</historique>

	<historique>
		<date>2009/12/12</date>
		<taux1>11.7242122896</taux1>
		<taux2>0.0852935767</taux2>
	</historique>

	<historique>
		<date>2009/12/13</date>
		<taux1>11.7302368674</taux1>
		<taux2>0.0852497704</taux2>
	</historique>

	<historique>
		<date>2009/12/14</date>
		<taux1>11.8459051376</taux1>
		<taux2>0.0844173567</taux2>
	</historique>

	<historique>
		<date>2009/12/15</date>
		<taux1>11.9994035077</taux1>
		<taux2>0.0833374758</taux2>
	</historique>

	<historique>
		<date>2009/12/16</date>
		<taux1>12.1290872701</taux1>
		<taux2>0.0824464346</taux2>
	</historique>

	<historique>
		<date>2009/12/17</date>
		<taux1>12.0079714935</taux1>
		<taux2>0.0832780125</taux2>
	</historique>

	<historique>
		<date>2009/12/18</date>
		<taux1>12.0728726394</taux1>
		<taux2>0.0828303279</taux2>
	</historique>

	<historique>
		<date>2009/12/19</date>
		<taux1>12.0318061068</taux1>
		<taux2>0.0831130415</taux2>
	</historique>

	<historique>
		<date>2009/12/20</date>
		<taux1>12.0785748443</taux1>
		<taux2>0.0827912244</taux2>
	</historique>

	<historique>
		<date>2009/12/21</date>
		<taux1>11.8976221356</taux1>
		<taux2>0.0840504084</taux2>
	</historique>

	<historique>
		<date>2009/12/22</date>
		<taux1>11.9111956425</taux1>
		<taux2>0.0839546281</taux2>
	</historique>

	<historique>
		<date>2009/12/23</date>
		<taux1>11.9506543939</taux1>
		<taux2>0.0836774261</taux2>
	</historique>

	<historique>
		<date>2009/12/24</date>
		<taux1>12.1666588008</taux1>
		<taux2>0.0821918340</taux2>
	</historique>

	<historique>
		<date>2009/12/25</date>
		<taux1>12.2061432554</taux1>
		<taux2>0.0819259597</taux2>
	</historique>

	<historique>
		<date>2009/12/26</date>
		<taux1>12.1600190341</taux1>
		<taux2>0.0822367134</taux2>
	</historique>

	<historique>
		<date>2009/12/27</date>
		<taux1>12.1950551287</taux1>
		<taux2>0.0820004493</taux2>
	</historique>

	<historique>
		<date>2009/12/28</date>
		<taux1>12.1655665386</taux1>
		<taux2>0.0821992134</taux2>
	</historique>

	<historique>
		<date>2009/12/29</date>
		<taux1>11.9113472106</taux1>
		<taux2>0.0839535598</taux2>
	</historique>

	<historique>
		<date>2009/12/30</date>
		<taux1>11.7203614981</taux1>
		<taux2>0.0853216004</taux2>
	</historique>

	<historique>
		<date>2009/12/31</date>
		<taux1>11.7675135031</taux1>
		<taux2>0.0849797198</taux2>
	</historique>
</XAG>
